langunittest/__init__.py
langunittest/agents/agent.py
langunittest/agents/tools/__init__.py
langunittest/utils/cli.py
langunittest/utils/colored_logging/__init__.py
langunittest-0.1.2.dist-info/LICENSE
langunittest-0.1.2.dist-info/METADATA
langunittest-0.1.2.dist-info/WHEEL
langunittest-0.1.2.dist-info/RECORD
