Metadata-Version: 2.3
Name: langunittest
Version: 0.1.2
Summary: LLM agent to facilitate the generation of unit test cases.
Author: johnklee
Author-email: puremonkey2001@yahoo.com.tw
Requires-Python: >=3.10,<4.0
Classifier: Programming Language :: Python :: 3
Classifier: Programming Language :: Python :: 3.10
Classifier: Programming Language :: Python :: 3.11
Classifier: Programming Language :: Python :: 3.12
Classifier: Programming Language :: Python :: 3.13
Requires-Dist: dotenv (>=0.9.9,<0.10.0)
Requires-Dist: gnureadline (>=8.2.13,<9.0.0)
Requires-Dist: google-adk (>=1.11.0,<2.0.0)
Requires-Dist: langfun (>=0.1.1,<0.2.0)
Requires-Dist: rich (>=14.1.0,<15.0.0)
Requires-Dist: termcolor (>=3.1.0,<4.0.0)
